mongodb_connect/__init__.py
mongodb_connect/mongo_crud.py
db_crud_automated-0.0.10.dist-info/LICENSE
db_crud_automated-0.0.10.dist-info/METADATA
db_crud_automated-0.0.10.dist-info/WHEEL
db_crud_automated-0.0.10.dist-info/top_level.txt
db_crud_automated-0.0.10.dist-info/RECORD
