Metadata-Version: 2.1
Name: db_crud_automated
Version: 0.0.10
Summary: A Python package for connecting with databases.
Home-page: https://github.com/shaheennabi/Unified-Database-Connector-Package
Author: shaheennabi
Author-email: ishaheennabi333@gmail.com
License: MIT
Classifier: Programming Language :: Python :: 3.7
Classifier: Programming Language :: Python :: 3.8
Classifier: Programming Language :: Python :: 3.9
Classifier: Operating System :: OS Independent
Requires-Python: >=3.7
License-File: LICENSE
Requires-Dist: pymongo
Requires-Dist: pandas
Requires-Dist: numpy
Requires-Dist: dnspython
Requires-Dist: pytest
Provides-Extra: testing
Requires-Dist: pytest>=7.1.3; extra == "testing"
Requires-Dist: mypy>=0.971; extra == "testing"
Requires-Dist: flake8>=5.0.4; extra == "testing"
Requires-Dist: tox>=3.25.1; extra == "testing"
Requires-Dist: black>=22.8.0; extra == "testing"
